syned/__init__.py
syned/syned_object.py
syned/__test/__init__.py
syned/__test/test.py
syned/beamline/__init__.py
syned/beamline/beamline.py
syned/beamline/beamline_element.py
syned/beamline/element_coordinates.py
syned/beamline/optical_element.py
syned/beamline/optical_element_with_surface_shape.py
syned/beamline/shape.py
syned/beamline/optical_elements/__init__.py
syned/beamline/optical_elements/absorbers/__init__.py
syned/beamline/optical_elements/absorbers/absorber.py
syned/beamline/optical_elements/absorbers/beam_stopper.py
syned/beamline/optical_elements/absorbers/filter.py
syned/beamline/optical_elements/absorbers/holed_filter.py
syned/beamline/optical_elements/absorbers/slit.py
syned/beamline/optical_elements/crystals/__init__.py
syned/beamline/optical_elements/crystals/crystal.py
syned/beamline/optical_elements/gratings/__init__.py
syned/beamline/optical_elements/gratings/grating.py
syned/beamline/optical_elements/ideal_elements/__init__.py
syned/beamline/optical_elements/ideal_elements/ideal_element.py
syned/beamline/optical_elements/ideal_elements/ideal_fzp.py
syned/beamline/optical_elements/ideal_elements/ideal_lens.py
syned/beamline/optical_elements/ideal_elements/screen.py
syned/beamline/optical_elements/mirrors/__init__.py
syned/beamline/optical_elements/mirrors/mirror.py
syned/beamline/optical_elements/multilayers/__init__.py
syned/beamline/optical_elements/multilayers/multilayer.py
syned/beamline/optical_elements/refractors/__init__.py
syned/beamline/optical_elements/refractors/crl.py
syned/beamline/optical_elements/refractors/interface.py
syned/beamline/optical_elements/refractors/lens.py
syned/storage_ring/__init__.py
syned/storage_ring/electron_beam.py
syned/storage_ring/empty_light_source.py
syned/storage_ring/light_source.py
syned/storage_ring/magnetic_structure.py
syned/storage_ring/magnetic_structures/__init__.py
syned/storage_ring/magnetic_structures/bending_magnet.py
syned/storage_ring/magnetic_structures/insertion_device.py
syned-1.0.48.dist-info/licenses/LICENSE
syned-1.0.48.dist-info/METADATA
syned-1.0.48.dist-info/WHEEL
syned-1.0.48.dist-info/top_level.txt
syned-1.0.48.dist-info/RECORD
