Metadata-Version: 2.4
Name: syned
Version: 1.0.48
Summary: SYNED (SYNchrotron Elements Dictionary) kernel library
Home-page: https://github.com/oasys-kit/syned
Download-URL: https://github.com/oasys-kit/syned
Author: Manuel Sanchez del Rio, Luca Rebuffi
Author-email: srio@esrf.eu
Maintainer: L Rebuffi and M Sanchez del Rio
Maintainer-email: srio@esrf.eu
License: GPLv3
Keywords: dictionary,glossary,synchrotronsimulation
Classifier: Development Status :: 5 - Production/Stable
Classifier: Environment :: Console
Classifier: Environment :: Plugins
Classifier: Programming Language :: Python :: 3
Classifier: Operating System :: POSIX
Classifier: Operating System :: Microsoft :: Windows
Classifier: Topic :: Scientific/Engineering :: Visualization
Classifier: Topic :: Software Development :: Libraries :: Python Modules
Classifier: Intended Audience :: Education
Classifier: Intended Audience :: Science/Research
Classifier: Intended Audience :: Developers
License-File: LICENSE
Requires-Dist: setuptools
Requires-Dist: numpy
Requires-Dist: scipy
Dynamic: author
Dynamic: author-email
Dynamic: classifier
Dynamic: description
Dynamic: download-url
Dynamic: home-page
Dynamic: keywords
Dynamic: license
Dynamic: license-file
Dynamic: maintainer
Dynamic: maintainer-email
Dynamic: requires-dist
Dynamic: summary
